odoo/addons/partner_tz/README.rst
odoo/addons/partner_tz/__init__.py
odoo/addons/partner_tz/__manifest__.py
odoo/addons/partner_tz/i18n/partner_tz.pot
odoo/addons/partner_tz/readme/CONTRIBUTORS.rst
odoo/addons/partner_tz/readme/DESCRIPTION.rst
odoo/addons/partner_tz/readme/ROADMAP.rst
odoo/addons/partner_tz/static/description/icon.png
odoo/addons/partner_tz/static/description/index.html
odoo/addons/partner_tz/tools/__init__.py
odoo/addons/partner_tz/tools/tz_utils.py
odoo/addons/partner_tz/views/res_partner.xml
odoo13_addon_partner_tz-13.0.1.0.1.dev10.dist-info/METADATA
odoo13_addon_partner_tz-13.0.1.0.1.dev10.dist-info/WHEEL
odoo13_addon_partner_tz-13.0.1.0.1.dev10.dist-info/top_level.txt
odoo13_addon_partner_tz-13.0.1.0.1.dev10.dist-info/RECORD
