Metadata-Version: 2.1
Name: odoo13-addon-partner-tz
Version: 13.0.1.0.1.dev10
Summary: Remove partner timezone default value and display on form
Home-page: https://github.com/OCA/partner-contact
Author: Camptocamp, Odoo Community Association (OCA)
Author-email: support@odoo-community.org
License: AGPL-3
Platform: UNKNOWN
Classifier: Programming Language :: Python
Classifier: Framework :: Odoo
Classifier: License :: OSI Approved :: GNU Affero General Public License v3
Classifier: Development Status :: 3 - Alpha
Requires-Python: >=3.5
Requires-Dist: odoo (<13.1dev,>=13.0a)
